README.rst
setup.cfg
setup.py
./__init__.py
./pagination.py
./product.py
./product.xml
./tryton.cfg
./website.py
./tests/__init__.py
./tests/test_pagination.py
./tests/test_product.py
./tests/test_views_depends.py
./view/attribute_form.xml
./view/attribute_list.xml
openlabs_nereid_webshop_elastic_search.egg-info/PKG-INFO
openlabs_nereid_webshop_elastic_search.egg-info/SOURCES.txt
openlabs_nereid_webshop_elastic_search.egg-info/dependency_links.txt
openlabs_nereid_webshop_elastic_search.egg-info/entry_points.txt
openlabs_nereid_webshop_elastic_search.egg-info/not-zip-safe
openlabs_nereid_webshop_elastic_search.egg-info/requires.txt
openlabs_nereid_webshop_elastic_search.egg-info/top_level.txt